MapGlobalToLocal/ProductMappingAtBrandForm.py
MapGlobalToLocal/ProductMappingAtCPG.py
MapGlobalToLocal/ProductMappingAtSKU.py
MapGlobalToLocal/__init__.py
MapGlobalToLocal-0.0.5.dist-info/LICENSE
MapGlobalToLocal-0.0.5.dist-info/METADATA
MapGlobalToLocal-0.0.5.dist-info/WHEEL
MapGlobalToLocal-0.0.5.dist-info/top_level.txt
MapGlobalToLocal-0.0.5.dist-info/RECORD
