Metadata-Version: 2.1
Name: MapGlobalToLocal
Version: 0.0.5
Summary: Library created to map two Dataset
Home-page: UNKNOWN
Author: Kunj Shah
Author-email: Kunj.Shah@unilever.com
License: UNKNOWN
Platform: UNKNOWN
Classifier: Programming Language :: Python :: 3
Classifier: License :: OSI Approved :: MIT License
Classifier: Operating System :: OS Independent
Requires-Python: >=3.7
License-File: LICENSE
Requires-Dist: pyspark
Requires-Dist: spark
Requires-Dist: pandas
Requires-Dist: databricks-sdk
